MANIFEST.in
README.md
setup.py
opclabs_mqttnet/__init__.py
opclabs_mqttnet.egg-info/PKG-INFO
opclabs_mqttnet.egg-info/SOURCES.txt
opclabs_mqttnet.egg-info/dependency_links.txt
opclabs_mqttnet.egg-info/not-zip-safe
opclabs_mqttnet.egg-info/requires.txt
opclabs_mqttnet.egg-info/top_level.txt
opclabs_mqttnet/OpcLabs.MqttNet/MQTTnet.Extensions.ManagedClient_4.3.7.1207.html
opclabs_mqttnet/OpcLabs.MqttNet/MQTTnet_4.3.7.1207.html
opclabs_mqttnet/OpcLabs.MqttNet/Microsoft.NETCore.Platforms_1.0.1.txt
opclabs_mqttnet/OpcLabs.MqttNet/Microsoft.NETCore.Platforms_1.1.0.txt
opclabs_mqttnet/OpcLabs.MqttNet/Microsoft.NETCore.Platforms_1.1.1.txt
opclabs_mqttnet/OpcLabs.MqttNet/Microsoft.NETCore.Platforms_2.0.0.txt
opclabs_mqttnet/OpcLabs.MqttNet/Microsoft.NETCore.Platforms_2.1.2.txt
opclabs_mqttnet/OpcLabs.MqttNet/Microsoft.NETCore.Portable.Compatibility_1.0.2.txt
opclabs_mqttnet/OpcLabs.MqttNet/Microsoft.NETCore.Runtime.CoreCLR_1.0.2.txt
opclabs_mqttnet/OpcLabs.MqttNet/Microsoft.NETCore.Runtime.CoreCLR_1.0.3.txt
opclabs_mqttnet/OpcLabs.MqttNet/Microsoft.NETCore.Targets_1.0.1.txt
opclabs_mqttnet/OpcLabs.MqttNet/Microsoft.NETCore.Targets_1.1.0.txt
opclabs_mqttnet/OpcLabs.MqttNet/Microsoft.NETCore.UniversalWindowsPlatform_6.2.10.txt
opclabs_mqttnet/OpcLabs.MqttNet/Microsoft.NETCore_5.0.2.txt
opclabs_mqttnet/OpcLabs.MqttNet/Microsoft.Net.Native.Compiler_1.7.6.txt
opclabs_mqttnet/OpcLabs.MqttNet/Microsoft.Net.Native.Compiler_2.2.8-rel-28605-00.txt
opclabs_mqttnet/OpcLabs.MqttNet/Microsoft.Net.UWPCoreRuntimeSdk_2.2.10.txt
opclabs_mqttnet/OpcLabs.MqttNet/Microsoft.Win32.Primitives_4.0.1.txt
opclabs_mqttnet/OpcLabs.MqttNet/Microsoft.Win32.Primitives_4.3.0.txt
opclabs_mqttnet/OpcLabs.MqttNet/NETStandard.Library_1.6.1.txt
opclabs_mqttnet/OpcLabs.MqttNet/System.AppContext_4.3.0.txt
opclabs_mqttnet/OpcLabs.MqttNet/System.Buffers_4.3.0.txt
opclabs_mqttnet/OpcLabs.MqttNet/System.Buffers_4.4.0.txt
opclabs_mqttnet/OpcLabs.MqttNet/System.Collections.Concurrent_4.0.12.txt
opclabs_mqttnet/OpcLabs.MqttNet/System.Collections.Concurrent_4.3.0.txt
opclabs_mqttnet/OpcLabs.MqttNet/System.Collections.Immutable_1.2.0.txt
opclabs_mqttnet/OpcLabs.MqttNet/System.Collections.NonGeneric_4.0.1.txt
