Metadata-Version: 2.4
Name: opclabs_mqttnet
Version: 5.83.1043
Summary: MQTT communication package based on MQTTnet and MQTTnet.Extensions.ManagedClient libraries by Christian Kratky.
Home-page: https://kb.opclabs.com/OpcLabs.MqttNet_communication_package?python
Author: CODE Consulting and Development, s.r.o.
Author-email: sales09@opclabs.com
Keywords: QuickOPC,OPC,UA,PubSub,MQTT
License-File: opclabs_mqttnet/OpcLabs.MqttNet/MQTTnet.Extensions.ManagedClient_4.3.7.1207.html
License-File: opclabs_mqttnet/OpcLabs.MqttNet/MQTTnet_4.3.7.1207.html
License-File: opclabs_mqttnet/OpcLabs.MqttNet/System.Private.ServiceModel_4.7.0.html
License-File: opclabs_mqttnet/OpcLabs.MqttNet/System.Reflection.Context_8.0.0.html
License-File: opclabs_mqttnet/OpcLabs.MqttNet/System.ServiceModel.Duplex_4.7.0.html
License-File: opclabs_mqttnet/OpcLabs.MqttNet/System.ServiceModel.Http_4.7.0.html
License-File: opclabs_mqttnet/OpcLabs.MqttNet/System.ServiceModel.NetTcp_4.7.0.html
License-File: opclabs_mqttnet/OpcLabs.MqttNet/System.ServiceModel.Primitives_4.7.0.html
License-File: opclabs_mqttnet/OpcLabs.MqttNet/System.ServiceModel.Security_4.7.0.html
License-File: opclabs_mqttnet/OpcLabs.MqttNet/Microsoft.NETCore.Platforms_1.0.1.txt
License-File: opclabs_mqttnet/OpcLabs.MqttNet/Microsoft.NETCore.Platforms_1.1.0.txt
License-File: opclabs_mqttnet/OpcLabs.MqttNet/Microsoft.NETCore.Platforms_1.1.1.txt
License-File: opclabs_mqttnet/OpcLabs.MqttNet/Microsoft.NETCore.Platforms_2.0.0.txt
License-File: opclabs_mqttnet/OpcLabs.MqttNet/Microsoft.NETCore.Platforms_2.1.2.txt
License-File: opclabs_mqttnet/OpcLabs.MqttNet/Microsoft.NETCore.Portable.Compatibility_1.0.2.txt
License-File: opclabs_mqttnet/OpcLabs.MqttNet/Microsoft.NETCore.Runtime.CoreCLR_1.0.2.txt
License-File: opclabs_mqttnet/OpcLabs.MqttNet/Microsoft.NETCore.Runtime.CoreCLR_1.0.3.txt
License-File: opclabs_mqttnet/OpcLabs.MqttNet/Microsoft.NETCore.Targets_1.0.1.txt
License-File: opclabs_mqttnet/OpcLabs.MqttNet/Microsoft.NETCore.Targets_1.1.0.txt
License-File: opclabs_mqttnet/OpcLabs.MqttNet/Microsoft.NETCore.UniversalWindowsPlatform_6.2.10.txt
License-File: opclabs_mqttnet/OpcLabs.MqttNet/Microsoft.NETCore_5.0.2.txt
License-File: opclabs_mqttnet/OpcLabs.MqttNet/Microsoft.Net.Native.Compiler_1.7.6.txt
License-File: opclabs_mqttnet/OpcLabs.MqttNet/Microsoft.Net.Native.Compiler_2.2.8-rel-28605-00.txt
License-File: opclabs_mqttnet/OpcLabs.MqttNet/Microsoft.Net.UWPCoreRuntimeSdk_2.2.10.txt
License-File: opclabs_mqttnet/OpcLabs.MqttNet/Microsoft.Win32.Primitives_4.0.1.txt
License-File: opclabs_mqttnet/OpcLabs.MqttNet/Microsoft.Win32.Primitives_4.3.0.txt
License-File: opclabs_mqttnet/OpcLabs.MqttNet/NETStandard.Library_1.6.1.txt
License-File: opclabs_mqttnet/OpcLabs.MqttNet/System.AppContext_4.3.0.txt
License-File: opclabs_mqttnet/OpcLabs.MqttNet/System.Buffers_4.3.0.txt
License-File: opclabs_mqttnet/OpcLabs.MqttNet/System.Buffers_4.4.0.txt
License-File: opclabs_mqttnet/OpcLabs.MqttNet/System.Collections.Concurrent_4.0.12.txt
License-File: opclabs_mqttnet/OpcLabs.MqttNet/System.Collections.Concurrent_4.3.0.txt
License-File: opclabs_mqttnet/OpcLabs.MqttNet/System.Collections.Immutable_1.2.0.txt
License-File: opclabs_mqttnet/OpcLabs.MqttNet/System.Collections.NonGeneric_4.0.1.txt
License-File: opclabs_mqttnet/OpcLabs.MqttNet/System.Collections.Specialized_4.0.1.txt
License-File: opclabs_mqttnet/OpcLabs.MqttNet/System.Collections_4.0.11.txt
License-File: opclabs_mqttnet/OpcLabs.MqttNet/System.Collections_4.3.0.txt
License-File: opclabs_mqttnet/OpcLabs.MqttNet/System.ComponentModel.EventBasedAsync_4.0.11.txt
License-File: opclabs_mqttnet/OpcLabs.MqttNet/System.ComponentModel.EventBasedAsync_4.3.0.txt
License-File: opclabs_mqttnet/OpcLabs.MqttNet/System.Console_4.3.0.txt
License-File: opclabs_mqttnet/OpcLabs.MqttNet/System.Data.Common_4.1.0.txt
License-File: opclabs_mqttnet/OpcLabs.MqttNet/System.Diagnostics.Contracts_4.3.0.txt
License-File: opclabs_mqttnet/OpcLabs.MqttNet/System.Diagnostics.Debug_4.0.11.txt
License-File: opclabs_mqttnet/OpcLabs.MqttNet/System.Diagnostics.Debug_4.3.0.txt
License-File: opclabs_mqttnet/OpcLabs.MqttNet/System.Diagnostics.DiagnosticSource_4.0.0.txt
License-File: opclabs_mqttnet/OpcLabs.MqttNet/System.Diagnostics.DiagnosticSource_4.3.0.txt
License-File: opclabs_mqttnet/OpcLabs.MqttNet/System.Diagnostics.StackTrace_4.0.2.txt
License-File: opclabs_mqttnet/OpcLabs.MqttNet/System.Diagnostics.Tools_4.3.0.txt
License-File: opclabs_mqttnet/OpcLabs.MqttNet/System.Diagnostics.Tracing_4.1.0.txt
License-File: opclabs_mqttnet/OpcLabs.MqttNet/System.Diagnostics.Tracing_4.3.0.txt
License-File: opclabs_mqttnet/OpcLabs.MqttNet/System.Globalization.Calendars_4.0.1.txt
License-File: opclabs_mqttnet/OpcLabs.MqttNet/System.Globalization.Calendars_4.3.0.txt
License-File: opclabs_mqttnet/OpcLabs.MqttNet/System.Globalization.Extensions_4.0.1.txt
License-File: opclabs_mqttnet/OpcLabs.MqttNet/System.Globalization.Extensions_4.3.0.txt
License-File: opclabs_mqttnet/OpcLabs.MqttNet/System.Globalization_4.0.11.txt
License-File: opclabs_mqttnet/OpcLabs.MqttNet/System.Globalization_4.3.0.txt
License-File: opclabs_mqttnet/OpcLabs.MqttNet/System.IO.Compression.ZipFile_4.3.0.txt
License-File: opclabs_mqttnet/OpcLabs.MqttNet/System.IO.Compression_4.1.0.txt
License-File: opclabs_mqttnet/OpcLabs.MqttNet/System.IO.Compression_4.3.0.txt
License-File: opclabs_mqttnet/OpcLabs.MqttNet/System.IO.FileSystem.Primitives_4.0.1.txt
License-File: opclabs_mqttnet/OpcLabs.MqttNet/System.IO.FileSystem.Primitives_4.3.0.txt
License-File: opclabs_mqttnet/OpcLabs.MqttNet/System.IO.FileSystem_4.0.1.txt
License-File: opclabs_mqttnet/OpcLabs.MqttNet/System.IO.FileSystem_4.3.0.txt
License-File: opclabs_mqttnet/OpcLabs.MqttNet/System.IO.IsolatedStorage_4.0.1.txt
License-File: opclabs_mqttnet/OpcLabs.MqttNet/System.IO_4.1.0.txt
License-File: opclabs_mqttnet/OpcLabs.MqttNet/System.IO_4.3.0.txt
License-File: opclabs_mqttnet/OpcLabs.MqttNet/System.Linq.Expressions_4.3.0.txt
License-File: opclabs_mqttnet/OpcLabs.MqttNet/System.Linq_4.1.0.txt
License-File: opclabs_mqttnet/OpcLabs.MqttNet/System.Linq_4.3.0.txt
License-File: opclabs_mqttnet/OpcLabs.MqttNet/System.Memory_4.5.0.txt
License-File: opclabs_mqttnet/OpcLabs.MqttNet/System.Net.Http.Rtc_4.0.1.txt
License-File: opclabs_mqttnet/OpcLabs.MqttNet/System.Net.Http_4.1.0.txt
License-File: opclabs_mqttnet/OpcLabs.MqttNet/System.Net.Http_4.3.0.txt
License-File: opclabs_mqttnet/OpcLabs.MqttNet/System.Net.Http_4.3.4.txt
License-File: opclabs_mqttnet/OpcLabs.MqttNet/System.Net.NameResolution_4.3.0.txt
License-File: opclabs_mqttnet/OpcLabs.MqttNet/System.Net.Primitives_4.0.11.txt
License-File: opclabs_mqttnet/OpcLabs.MqttNet/System.Net.Primitives_4.3.0.txt
License-File: opclabs_mqttnet/OpcLabs.MqttNet/System.Net.Requests_4.0.11.txt
License-File: opclabs_mqttnet/OpcLabs.MqttNet/System.Net.Requests_4.3.0.txt
License-File: opclabs_mqttnet/OpcLabs.MqttNet/System.Net.Security_4.3.2.txt
License-File: opclabs_mqttnet/OpcLabs.MqttNet/System.Net.Sockets_4.1.0.txt
License-File: opclabs_mqttnet/OpcLabs.MqttNet/System.Net.Sockets_4.3.0.txt
License-File: opclabs_mqttnet/OpcLabs.MqttNet/System.Net.WebHeaderCollection_4.0.1.txt
License-File: opclabs_mqttnet/OpcLabs.MqttNet/System.Net.WebHeaderCollection_4.3.0.txt
License-File: opclabs_mqttnet/OpcLabs.MqttNet/System.Net.WebSockets.Client_4.3.2.txt
License-File: opclabs_mqttnet/OpcLabs.MqttNet/System.Net.WebSockets_4.3.0.txt
License-File: opclabs_mqttnet/OpcLabs.MqttNet/System.Numerics.Vectors.WindowsRuntime_4.0.1.txt
License-File: opclabs_mqttnet/OpcLabs.MqttNet/System.Numerics.Vectors_4.4.0.txt
License-File: opclabs_mqttnet/OpcLabs.MqttNet/System.ObjectModel_4.0.12.txt
License-File: opclabs_mqttnet/OpcLabs.MqttNet/System.ObjectModel_4.3.0.txt
License-File: opclabs_mqttnet/OpcLabs.MqttNet/System.Private.DataContractSerialization_4.1.2.txt
License-File: opclabs_mqttnet/OpcLabs.MqttNet/System.Private.DataContractSerialization_4.3.0.txt
License-File: opclabs_mqttnet/OpcLabs.MqttNet/System.Reflection.DispatchProxy_4.5.0.txt
License-File: opclabs_mqttnet/OpcLabs.MqttNet/System.Reflection.Emit.ILGeneration_4.0.1.txt
License-File: opclabs_mqttnet/OpcLabs.MqttNet/System.Reflection.Emit.ILGeneration_4.3.0.txt
License-File: opclabs_mqttnet/OpcLabs.MqttNet/System.Reflection.Emit.Lightweight_4.0.1.txt
License-File: opclabs_mqttnet/OpcLabs.MqttNet/System.Reflection.Emit.Lightweight_4.3.0.txt
License-File: opclabs_mqttnet/OpcLabs.MqttNet/System.Reflection.Emit_4.0.1.txt
License-File: opclabs_mqttnet/OpcLabs.MqttNet/System.Reflection.Emit_4.3.0.txt
License-File: opclabs_mqttnet/OpcLabs.MqttNet/System.Reflection.Extensions_4.0.1.txt
License-File: opclabs_mqttnet/OpcLabs.MqttNet/System.Reflection.Extensions_4.3.0.txt
License-File: opclabs_mqttnet/OpcLabs.MqttNet/System.Reflection.Metadata_1.3.0.txt
License-File: opclabs_mqttnet/OpcLabs.MqttNet/System.Reflection.Primitives_4.0.1.txt
License-File: opclabs_mqttnet/OpcLabs.MqttNet/System.Reflection.Primitives_4.3.0.txt
License-File: opclabs_mqttnet/OpcLabs.MqttNet/System.Reflection.TypeExtensions_4.1.0.txt
License-File: opclabs_mqttnet/OpcLabs.MqttNet/System.Reflection.TypeExtensions_4.3.0.txt
License-File: opclabs_mqttnet/OpcLabs.MqttNet/System.Reflection_4.1.0.txt
License-File: opclabs_mqttnet/OpcLabs.MqttNet/System.Reflection_4.3.0.txt
License-File: opclabs_mqttnet/OpcLabs.MqttNet/System.Resources.ResourceManager_4.0.1.txt
License-File: opclabs_mqttnet/OpcLabs.MqttNet/System.Resources.ResourceManager_4.3.0.txt
License-File: opclabs_mqttnet/OpcLabs.MqttNet/System.Runtime.CompilerServices.Unsafe_4.5.0.txt
License-File: opclabs_mqttnet/OpcLabs.MqttNet/System.Runtime.CompilerServices.Unsafe_4.5.2.txt
License-File: opclabs_mqttnet/OpcLabs.MqttNet/System.Runtime.Extensions_4.1.0.txt
License-File: opclabs_mqttnet/OpcLabs.MqttNet/System.Runtime.Extensions_4.3.0.txt
License-File: opclabs_mqttnet/OpcLabs.MqttNet/System.Runtime.Handles_4.0.1.txt
License-File: opclabs_mqttnet/OpcLabs.MqttNet/System.Runtime.Handles_4.3.0.txt
License-File: opclabs_mqttnet/OpcLabs.MqttNet/System.Runtime.InteropServices.RuntimeInformation_4.3.0.txt
License-File: opclabs_mqttnet/OpcLabs.MqttNet/System.Runtime.InteropServices.WindowsRuntime_4.0.1.txt
License-File: opclabs_mqttnet/OpcLabs.MqttNet/System.Runtime.InteropServices.WindowsRuntime_4.3.0.txt
License-File: opclabs_mqttnet/OpcLabs.MqttNet/System.Runtime.InteropServices_4.1.0.txt
License-File: opclabs_mqttnet/OpcLabs.MqttNet/System.Runtime.InteropServices_4.3.0.txt
License-File: opclabs_mqttnet/OpcLabs.MqttNet/System.Runtime.Numerics_4.0.1.txt
License-File: opclabs_mqttnet/OpcLabs.MqttNet/System.Runtime.Numerics_4.3.0.txt
License-File: opclabs_mqttnet/OpcLabs.MqttNet/System.Runtime.Serialization.Json_4.0.3.txt
License-File: opclabs_mqttnet/OpcLabs.MqttNet/System.Runtime.Serialization.Primitives_4.1.1.txt
License-File: opclabs_mqttnet/OpcLabs.MqttNet/System.Runtime.Serialization.Primitives_4.3.0.txt
License-File: opclabs_mqttnet/OpcLabs.MqttNet/System.Runtime.Serialization.Xml_4.1.2.txt
License-File: opclabs_mqttnet/OpcLabs.MqttNet/System.Runtime.Serialization.Xml_4.3.0.txt
License-File: opclabs_mqttnet/OpcLabs.MqttNet/System.Runtime.WindowsRuntime.UI.Xaml_4.0.1.txt
License-File: opclabs_mqttnet/OpcLabs.MqttNet/System.Runtime.WindowsRuntime_4.0.11.txt
License-File: opclabs_mqttnet/OpcLabs.MqttNet/System.Runtime.WindowsRuntime_4.3.0.txt
License-File: opclabs_mqttnet/OpcLabs.MqttNet/System.Runtime_4.1.0.txt
License-File: opclabs_mqttnet/OpcLabs.MqttNet/System.Runtime_4.3.0.txt
License-File: opclabs_mqttnet/OpcLabs.MqttNet/System.Security.AccessControl_4.5.0.txt
License-File: opclabs_mqttnet/OpcLabs.MqttNet/System.Security.Claims_4.3.0.txt
License-File: opclabs_mqttnet/OpcLabs.MqttNet/System.Security.Cryptography.Algorithms_4.2.0.txt
License-File: opclabs_mqttnet/OpcLabs.MqttNet/System.Security.Cryptography.Algorithms_4.3.0.txt
License-File: opclabs_mqttnet/OpcLabs.MqttNet/System.Security.Cryptography.Cng_4.2.0.txt
License-File: opclabs_mqttnet/OpcLabs.MqttNet/System.Security.Cryptography.Cng_4.3.0.txt
License-File: opclabs_mqttnet/OpcLabs.MqttNet/System.Security.Cryptography.Cng_4.4.0.txt
License-File: opclabs_mqttnet/OpcLabs.MqttNet/System.Security.Cryptography.Cng_4.5.0.txt
License-File: opclabs_mqttnet/OpcLabs.MqttNet/System.Security.Cryptography.Csp_4.0.0.txt
License-File: opclabs_mqttnet/OpcLabs.MqttNet/System.Security.Cryptography.Csp_4.3.0.txt
License-File: opclabs_mqttnet/OpcLabs.MqttNet/System.Security.Cryptography.Encoding_4.0.0.txt
License-File: opclabs_mqttnet/OpcLabs.MqttNet/System.Security.Cryptography.Encoding_4.3.0.txt
License-File: opclabs_mqttnet/OpcLabs.MqttNet/System.Security.Cryptography.OpenSsl_4.0.0.txt
License-File: opclabs_mqttnet/OpcLabs.MqttNet/System.Security.Cryptography.OpenSsl_4.3.0.txt
License-File: opclabs_mqttnet/OpcLabs.MqttNet/System.Security.Cryptography.Pkcs_4.5.0.txt
License-File: opclabs_mqttnet/OpcLabs.MqttNet/System.Security.Cryptography.Primitives_4.0.0.txt
License-File: opclabs_mqttnet/OpcLabs.MqttNet/System.Security.Cryptography.Primitives_4.3.0.txt
License-File: opclabs_mqttnet/OpcLabs.MqttNet/System.Security.Cryptography.X509Certificates_4.1.0.txt
License-File: opclabs_mqttnet/OpcLabs.MqttNet/System.Security.Cryptography.X509Certificates_4.3.0.txt
License-File: opclabs_mqttnet/OpcLabs.MqttNet/System.Security.Cryptography.Xml_4.5.0.txt
License-File: opclabs_mqttnet/OpcLabs.MqttNet/System.Security.Permissions_4.5.0.txt
License-File: opclabs_mqttnet/OpcLabs.MqttNet/System.Security.Principal.Windows_4.3.0.txt
License-File: opclabs_mqttnet/OpcLabs.MqttNet/System.Security.Principal.Windows_4.5.0.txt
License-File: opclabs_mqttnet/OpcLabs.MqttNet/System.Security.Principal_4.3.0.txt
License-File: opclabs_mqttnet/OpcLabs.MqttNet/System.Text.Encoding.CodePages_4.5.1.txt
License-File: opclabs_mqttnet/OpcLabs.MqttNet/System.Text.Encoding.Extensions_4.0.11.txt
License-File: opclabs_mqttnet/OpcLabs.MqttNet/System.Text.Encoding.Extensions_4.3.0.txt
License-File: opclabs_mqttnet/OpcLabs.MqttNet/System.Text.Encoding_4.0.11.txt
License-File: opclabs_mqttnet/OpcLabs.MqttNet/System.Text.Encoding_4.3.0.txt
License-File: opclabs_mqttnet/OpcLabs.MqttNet/System.Text.RegularExpressions_4.1.0.txt
License-File: opclabs_mqttnet/OpcLabs.MqttNet/System.Text.RegularExpressions_4.3.0.txt
License-File: opclabs_mqttnet/OpcLabs.MqttNet/System.Threading.Overlapped_4.3.0.txt
License-File: opclabs_mqttnet/OpcLabs.MqttNet/System.Threading.Tasks.Extensions_4.0.0.txt
License-File: opclabs_mqttnet/OpcLabs.MqttNet/System.Threading.Tasks.Extensions_4.3.0.txt
License-File: opclabs_mqttnet/OpcLabs.MqttNet/System.Threading.Tasks_4.0.11.txt
License-File: opclabs_mqttnet/OpcLabs.MqttNet/System.Threading.Tasks_4.3.0.txt
License-File: opclabs_mqttnet/OpcLabs.MqttNet/System.Threading.ThreadPool_4.3.0.txt
License-File: opclabs_mqttnet/OpcLabs.MqttNet/System.Threading.Thread_4.3.0.txt
License-File: opclabs_mqttnet/OpcLabs.MqttNet/System.Threading.Timer_4.3.0.txt
License-File: opclabs_mqttnet/OpcLabs.MqttNet/System.Threading_4.0.11.txt
License-File: opclabs_mqttnet/OpcLabs.MqttNet/System.Threading_4.3.0.txt
License-File: opclabs_mqttnet/OpcLabs.MqttNet/System.Xml.ReaderWriter_4.0.11.txt
License-File: opclabs_mqttnet/OpcLabs.MqttNet/System.Xml.ReaderWriter_4.3.0.txt
License-File: opclabs_mqttnet/OpcLabs.MqttNet/System.Xml.XDocument_4.3.0.txt
License-File: opclabs_mqttnet/OpcLabs.MqttNet/System.Xml.XmlDocument_4.0.1.txt
License-File: opclabs_mqttnet/OpcLabs.MqttNet/System.Xml.XmlDocument_4.3.0.txt
License-File: opclabs_mqttnet/OpcLabs.MqttNet/System.Xml.XmlSerializer_4.0.11.txt
License-File: opclabs_mqttnet/OpcLabs.MqttNet/System.Xml.XmlSerializer_4.3.0.txt
License-File: opclabs_mqttnet/OpcLabs.MqttNet/runtime.native.System.IO.Compression_4.1.0.txt
License-File: opclabs_mqttnet/OpcLabs.MqttNet/runtime.native.System.IO.Compression_4.3.0.txt
License-File: opclabs_mqttnet/OpcLabs.MqttNet/runtime.native.System.Net.Http_4.0.1.txt
License-File: opclabs_mqttnet/OpcLabs.MqttNet/runtime.native.System.Net.Http_4.3.0.txt
License-File: opclabs_mqttnet/OpcLabs.MqttNet/runtime.native.System.Net.Security_4.3.0.txt
License-File: opclabs_mqttnet/OpcLabs.MqttNet/runtime.native.System.Security.Cryptography.Apple_4.3.0.txt
License-File: opclabs_mqttnet/OpcLabs.MqttNet/runtime.native.System.Security.Cryptography.OpenSsl_4.3.0.txt
License-File: opclabs_mqttnet/OpcLabs.MqttNet/runtime.native.System.Security.Cryptography.OpenSsl_4.3.2.txt
License-File: opclabs_mqttnet/OpcLabs.MqttNet/runtime.native.System.Security.Cryptography_4.0.0.txt
License-File: opclabs_mqttnet/OpcLabs.MqttNet/runtime.native.System_4.0.0.txt
License-File: opclabs_mqttnet/OpcLabs.MqttNet/runtime.native.System_4.3.0.txt
License-File: opclabs_mqttnet/OpcLabs.MqttNet/runtime.win10-arm.Microsoft.Net.UWPCoreRuntimeSdk_2.2.10.txt
License-File: opclabs_mqttnet/OpcLabs.MqttNet/runtime.win10-x64.Microsoft.Net.UWPCoreRuntimeSdk_2.2.10.txt
License-File: opclabs_mqttnet/OpcLabs.MqttNet/runtime.win10-x86.Microsoft.Net.UWPCoreRuntimeSdk_2.2.10.txt
License-File: opclabs_mqttnet/OpcLabs.MqttNet/runtime.win7.System.Private.Uri_4.3.0.txt
Requires-Dist: opclabs_quickopc
Dynamic: author
Dynamic: author-email
Dynamic: description
Dynamic: description-content-type
Dynamic: home-page
Dynamic: keywords
Dynamic: license-file
Dynamic: requires-dist
Dynamic: summary
